jsontoxl.py
jsontoxl-1.0.dist-info/METADATA
jsontoxl-1.0.dist-info/WHEEL
jsontoxl-1.0.dist-info/top_level.txt
jsontoxl-1.0.dist-info/RECORD
