Metadata-Version: 2.1
Name: jsontoxl
Version: 1.0
Summary: A script to convert JSON to Excel hierarchy
Home-page: UNKNOWN
Author: Mahesh Reddy
Author-email: maheshyamana123@gmail.com
License: UNKNOWN
Platform: UNKNOWN
